model_protocol_sdk/__init__.py
model_protocol_sdk/abstract_model.py
model_protocol_sdk/http_model_server.py
model_protocol_sdk/model_pb2.py
model_protocol_sdk/model_pb2_grpc.py
model_protocol_sdk/pusher.py
model_protocol_sdk/model/__init__.py
model_protocol_sdk/model/model_category.py
model_protocol_sdk-0.0.8.dist-info/METADATA
model_protocol_sdk-0.0.8.dist-info/WHEEL
model_protocol_sdk-0.0.8.dist-info/top_level.txt
model_protocol_sdk-0.0.8.dist-info/RECORD
