Metadata-Version: 2.1
Name: model_protocol_sdk
Version: 0.0.8
Summary: 模型协议开发SDK
Author: fuhl
Requires-Python: >=3.8
Requires-Dist: grpcio >=1.48.2
Requires-Dist: grpcio-tools >=1.48.2
Requires-Dist: paho-mqtt >=1.6.1
Requires-Dist: fastapi >=0.111.1
Requires-Dist: uvicorn >=0.24.0
Requires-Dist: pydantic >=2.5.0
Requires-Dist: aiohttp >=3.9.0
